aws_cfn_kafka_admin_provider/__init__.py
aws_cfn_kafka_admin_provider/aws_cfn_kafka_admin_provider.py
aws_cfn_kafka_admin_provider/cli.py
aws_cfn_kafka_admin_provider/model.py
aws_cfn_kafka_admin_provider-0.6.0.dist-info/entry_points.txt
aws_cfn_kafka_admin_provider-0.6.0.dist-info/LICENSE
aws_cfn_kafka_admin_provider-0.6.0.dist-info/WHEEL
aws_cfn_kafka_admin_provider-0.6.0.dist-info/METADATA
aws_cfn_kafka_admin_provider-0.6.0.dist-info/RECORD
