Metadata-Version: 2.1
Name: aws-cfn-kafka-admin-provider
Version: 0.6.0
Summary: Converts simple YAML definitions of kafka ACLs and topics into AWS CFN templates
License: MPL-2.0
Author: John Preston
Author-email: john@ews-network.net
Requires-Python: >=3.7,<4.0
Classifier: Development Status :: 4 - Beta
Classifier: Intended Audience :: Developers
Classifier: Intended Audience :: Information Technology
Classifier: Intended Audience :: System Administrators
Classifier: License :: OSI Approved
Classifier: License :: OSI Approved :: Mozilla Public License 2.0 (MPL 2.0)
Classifier: Natural Language :: English
Classifier: Programming Language :: Python :: 3
Classifier: Programming Language :: Python :: 3.7
Classifier: Programming Language :: Python :: 3.8
Classifier: Programming Language :: Python :: 3.9
Requires-Dist: aws-custom-ews-kafka-resources (>=0.2.0,<0.3.0)
Requires-Dist: jsonschema (>=3.2.0,<4.0.0)
Requires-Dist: pydantic (>=1.8.2,<2.0.0)
Requires-Dist: troposphere (>=3.0,<4.0)
